sqlean_driver/__init__.py
sqlean_driver/py.typed
sqlean_driver-0.2.0.dist-info/METADATA
sqlean_driver-0.2.0.dist-info/WHEEL
sqlean_driver-0.2.0.dist-info/entry_points.txt
sqlean_driver-0.2.0.dist-info/licenses/LICENSE.txt
sqlean_driver-0.2.0.dist-info/RECORD
