Metadata-Version: 2.3
Name: sqlean-driver
Version: 0.2.0
Summary: SQLAlchemy dialect for the sqlean.py SQLite wrapper
Project-URL: Changelog, https://github.com/edgarrmondragon/sqlean-driver/blob/main/CHANGELOG.md
Project-URL: Documentation, https://github.com/edgarrmondragon/sqlean-driver#readme
Project-URL: Issues, https://github.com/edgarrmondragon/sqlean-driver/issues
Project-URL: Source, https://github.com/edgarrmondragon/sqlean-driver
Author-email: Edgar Ramírez Mondragón <edgarrm358@gmail.com>
Maintainer-email: Edgar Ramírez Mondragón <edgarrm358@gmail.com>
License: MIT License
License-File: LICENSE.txt
Classifier: Development Status :: 4 - Beta
Classifier: Intended Audience :: Developers
Classifier: Intended Audience :: Education
Classifier: Intended Audience :: Information Technology
Classifier: Intended Audience :: System Administrators
Classifier: License :: OSI Approved :: MIT License
Classifier: Operating System :: OS Independent
Classifier: Programming Language :: Python :: 3 :: Only
Classifier: Programming Language :: Python :: 3.8
Classifier: Programming Language :: Python :: 3.9
Classifier: Programming Language :: Python :: 3.10
Classifier: Programming Language :: Python :: 3.11
Classifier: Programming Language :: Python :: 3.12
Classifier: Programming Language :: Python :: 3.13
Classifier: Programming Language :: Python :: Implementation :: CPython
Classifier: Programming Language :: SQL
Classifier: Topic :: Database
Classifier: Topic :: Software Development
Classifier: Topic :: Software Development :: Libraries
Classifier: Topic :: Software Development :: Libraries :: Application Frameworks
Classifier: Topic :: Software Development :: Libraries :: Python Modules
Classifier: Typing :: Typed
Requires-Python: >=3.8
Requires-Dist: sqlalchemy>=1.4
Requires-Dist: sqlean-py<3.47,>=0.21.5.1; python_version < '3.9'
Requires-Dist: sqlean-py>=0.21.5.1; python_version >= '3.9'
Provides-Extra: coverage
Requires-Dist: coverage[toml]>=7.4.2; extra == 'coverage'
Provides-Extra: testing
Requires-Dist: coverage[toml]>=7.4.2; extra == 'testing'
Requires-Dist: pytest; extra == 'testing'
Requires-Dist: pytest-github-actions-annotate-failures; extra == 'testing'
Provides-Extra: typing
Requires-Dist: mypy>=1; extra == 'typing'
